leaf/__init__.py
leaf/admin.py
leaf/apps.py
leaf/forms.py
leaf/helpers.py
leaf/migrations/0001_initial.py
leaf/migrations/0002_add_page_node.py
leaf/migrations/0003_auto_20200505_2157.py
leaf/migrations/__init__.py
leaf/models.py
leaf/page.py
leaf/static/leaf/css/admin.css
leaf/tests/test_admin.py
leaf/tests/test_forms.py
leaf/tests/test_models.py
leaf/tests/test_page.py
leaf/tests/test_pages_helpers.py
leaf/tests/test_views.py
leaf/urls.py
leaf/views.py
django3_leaf-3.0.1.dist-info/LICENSE
django3_leaf-3.0.1.dist-info/WHEEL
django3_leaf-3.0.1.dist-info/METADATA
django3_leaf-3.0.1.dist-info/RECORD
