Metadata-Version: 2.1
Name: django3-leaf
Version: 3.0.1
Summary: Render and serve django templates based on URL.
Home-page: https://github.com/ImaginaryLandscape/django3-leaf
License: BSD
Author: Ryan Senkbeil
Author-email: sysadmin@corecreative.com
Maintainer: Imagescape
Maintainer-email: info@imagescape.com
Requires-Python: >=3.7,<4.0
Classifier: License :: Other/Proprietary License
Classifier: Programming Language :: Python :: 3
Classifier: Programming Language :: Python :: 3.10
Classifier: Programming Language :: Python :: 3.7
Classifier: Programming Language :: Python :: 3.8
Classifier: Programming Language :: Python :: 3.9
Requires-Dist: django-mptt (>=0.11.0)
Requires-Dist: six (>=1.16.0)
